{"Macro":[{"Data":{"UnitName":"Neji","CFrame":"4.380859375, -46.6732177734375, -34.846343994140625","Index":1},"Time":0,"Event":"Summon"},{"Data":{"UnitName":"Neji","CFrame":"6.554443359375, -46.6732177734375, -34.495513916015625","Index":2},"Time":0,"Event":"Summon"},{"Data":{"UnitName":"Neji","CFrame":"1.9111328125, -46.6732177734375, -34.776031494140625","Index":3},"Time":0,"Event":"Summon"},{"Data":{"UnitName":"Neji","CFrame":"-0.150390625, -46.6732177734375, -34.380279541015625","Index":4},"Time":1.26,"Event":"Summon"},{"Data":{"UnitName":"Neji","CFrame":"4.424560546875, -46.6732177734375, -32.535308837890625","Index":5},"Time":15.03,"Event":"Summon"},{"Data":{"UnitName":"Neji","CFrame":"6.633056640625, -46.6732177734375, -32.429595947265625","Index":6},"Time":17.51,"Event":"Summon"},{"Data":{"UnitName":"Neji","CFrame":"2.054443359375, -46.6732177734375, -32.362701416015625","Index":7},"Time":22.29,"Event":"Summon"},{"Data":{"UnitName":"Neji","CFrame":"-0.189208984375, -46.6732177734375, -32.163482666015625","Index":8},"Time":26.94,"Event":"Summon"},{"Data":{"Index":1},"Time":37.16,"Event":"Upgrade"},{"Data":{"Index":1},"Time":45.73,"Event":"Upgrade"},{"Data":{"Index":3},"Time":62.94,"Event":"Upgrade"},{"Data":{"Index":3},"Time":63.32,"Event":"Upgrade"},{"Data":{"Index":1},"Time":69.16,"Event":"Upgrade"},{"Data":{"Index":1},"Time":74.69,"Event":"Upgrade"},{"Data":{"Index":1},"Time":87.8,"Event":"Upgrade"},{"Data":{"Index":1},"Time":95.43,"Event":"Upgrade"},{"Data":{"Index":1},"Time":99.94,"Event":"Upgrade"},{"Data":{"Index":1},"Time":104.16,"Event":"Upgrade"},{"Data":{"Index":2},"Time":110.53,"Event":"Upgrade"},{"Data":{"Index":2},"Time":110.83,"Event":"Upgrade"},{"Data":{"Index":4},"Time":114.86,"Event":"Upgrade"},{"Data":{"Index":4},"Time":119.17,"Event":"Upgrade"},{"Data":{"Index":3},"Time":126.3,"Event":"Upgrade"},{"Data":{"Index":2},"Time":128.72,"Event":"Upgrade"},{"Data":{"Index":4},"Time":136.94,"Event":"Upgrade"},{"Data":{"Index":3},"Time":141.84,"Event":"Upgrade"},{"Data":{"Index":3},"Time":144.86,"Event":"Upgrade"},{"Data":{"Index":3},"Time":149.64,"Event":"Upgrade"},{"Data":{"Index":3},"Time":153.87,"Event":"Upgrade"},{"Data":{"Index":3},"Time":158.78,"Event":"Upgrade"},{"Data":{"Index":2},"Time":162.11,"Event":"Upgrade"},{"Data":{"Index":5},"Time":164.69,"Event":"Upgrade"},{"Data":{"Index":5},"Time":165.26,"Event":"Upgrade"},{"Data":{"Index":7},"Time":170.72,"Event":"Upgrade"},{"Data":{"Index":7},"Time":175.6,"Event":"Upgrade"},{"Data":{"Index":6},"Time":180.58,"Event":"Upgrade"},{"Data":{"Index":6},"Time":181.11,"Event":"Upgrade"},{"Data":{"Index":8},"Time":183.49,"Event":"Upgrade"},{"Data":{"Index":8},"Time":184.63,"Event":"Upgrade"},{"Data":{"Index":2},"Time":194.44,"Event":"Upgrade"},{"Data":{"Index":2},"Time":197.06,"Event":"Upgrade"},{"Data":{"Index":2},"Time":199.36,"Event":"Upgrade"},{"Data":{"Index":2},"Time":199.6,"Event":"Upgrade"},{"Data":{"Index":4},"Time":202.88,"Event":"Upgrade"},{"Data":{"Index":4},"Time":209.98,"Event":"Upgrade"},{"Data":{"Index":4},"Time":212.92,"Event":"Upgrade"},{"Data":{"Index":4},"Time":214.06,"Event":"Upgrade"},{"Data":{"Index":4},"Time":216.84,"Event":"Upgrade"},{"Data":{"Index":5},"Time":220.81,"Event":"Upgrade"},{"Data":{"Index":5},"Time":221.16,"Event":"Upgrade"},{"Data":{"Index":5},"Time":225.61,"Event":"Upgrade"},{"Data":{"Index":5},"Time":228.44,"Event":"Upgrade"},{"Data":{"Index":5},"Time":231.59,"Event":"Upgrade"},{"Data":{"Index":5},"Time":234.95,"Event":"Upgrade"},{"Data":{"Index":7},"Time":239.02,"Event":"Upgrade"},{"Data":{"Index":7},"Time":239.7,"Event":"Upgrade"},{"Data":{"Index":7},"Time":240.04,"Event":"Upgrade"},{"Data":{"Index":7},"Time":242.83,"Event":"Upgrade"},{"Data":{"Index":7},"Time":244.95,"Event":"Upgrade"},{"Data":{"Index":7},"Time":247.14,"Event":"Upgrade"},{"Data":{"Index":6},"Time":250.27,"Event":"Upgrade"},{"Data":{"Index":6},"Time":251.49,"Event":"Upgrade"},{"Data":{"Index":6},"Time":254.82,"Event":"Upgrade"},{"Data":{"Index":6},"Time":255.55,"Event":"Upgrade"},{"Data":{"Index":6},"Time":255.98,"Event":"Upgrade"},{"Data":{"Index":6},"Time":259.35,"Event":"Upgrade"},{"Data":{"Index":8},"Time":263.8,"Event":"Upgrade"},{"Data":{"Index":8},"Time":265.95,"Event":"Upgrade"},{"Data":{"Index":8},"Time":268.77,"Event":"Upgrade"},{"Data":{"Index":8},"Time":271.43,"Event":"Upgrade"},{"Data":{"Index":8},"Time":275.42,"Event":"Upgrade"},{"Data":{"Index":8},"Time":278.32,"Event":"Upgrade"}],"Config":{"Macro Type":"Paid","Select Macro Must Wait Event":["Sell","ChangePriority","UseSpecialMove","UseMultipleAbilities","AutoToggle","VoteWaveConfirm","VoteGameMode","SpeedChange","AutoSkipWaves_CHANGE"],"Timer Type":"First Enemy","Unit":{"RoyxLeader_Neji":{"Orb":"N/A","Level":"N/A","Leader":true},"Neji":{"Orb":"N/A","Level":10}}}}